pyreverb/__init__.py
pyreverb/reverb.py
pyreverb/reverb_errors.py
pyreverb/reverb_kernel.py
pyreverb/Exemple/client.py
pyreverb/Exemple/launcher.py
pyreverb/Exemple/server.py
pyreverb/Exemple/shooter_objects.py
pyreverb-1.6.5.dist-info/licenses/LICENSE
pyreverb-1.6.5.dist-info/METADATA
pyreverb-1.6.5.dist-info/WHEEL
pyreverb-1.6.5.dist-info/top_level.txt
pyreverb-1.6.5.dist-info/RECORD
