Metadata-Version: 2.4
Name: pyreverb
Version: 1.6.5
Summary: Multiplayer library
Author: Labo
License: Apache License Version 2.0
Project-URL: Homepage, https://github.com/LeLaboDuGame/PyReverb
Project-URL: Source, https://github.com/LeLaboDuGame/PyReverb
Requires-Python: >=3.13
License-File: LICENSE
Requires-Dist: colorama
Requires-Dist: pygame
Dynamic: license-file
